acmagent
