Metadata-Version: 1.1
Name: acmagent
Version: 1.0.2
Summary: ACM agent - automates ACM certificates
Home-page: https://github.com/b-b3rn4rd/acmagent
Author: Bernard Baltrusaitis
Author-email: bernard@runawaylover.info
License: MIT
Keywords: acm aws ssl certificates
Platform: UNKNOWN
Classifier: Development Status :: 4 - Beta
Classifier: Intended Audience :: Developers
Classifier: Intended Audience :: System Administrators
Classifier: License :: OSI Approved :: MIT License
Classifier: Programming Language :: Python :: 2.7
Classifier: Programming Language :: Python :: 3
Classifier: Environment :: Console
